COPYING
MANIFEST.in
README.rst
setup.py
django_hipchat/__init__.py
django_hipchat/api.py
django_hipchat/app_settings.py
django_hipchat/backends.py
django_hipchat/models.py
django_hipchat.egg-info/PKG-INFO
django_hipchat.egg-info/SOURCES.txt
django_hipchat.egg-info/dependency_links.txt
django_hipchat.egg-info/requires.txt
django_hipchat.egg-info/top_level.txt
django_hipchat/templates/django_hipchat/auth_token
django_hipchat/templates/django_hipchat/color
django_hipchat/templates/django_hipchat/from
django_hipchat/templates/django_hipchat/message
django_hipchat/templates/django_hipchat/room_id