Metadata-Version: 1.0
Name: django-hipchat
Version: 1.1.1
Summary: Provides easy-to-use integration between Django projects and the hipchat group chat and IM tool.
Home-page: UNKNOWN
Author: Chris Lamb
Author-email: chris@chris-lamb.co.uk
License: BSD
Platform: UNKNOWN
